MANIFEST.in
README.md
VERSION
setup.py
teapot/__init__.py
teapot/attendee.py
teapot/build.py
teapot/command.py
teapot/environment.py
teapot/error.py
teapot/globals.py
teapot/log.py
teapot/main.py
teapot/memoized.py
teapot/options.py
teapot/party.py
teapot/party_path.py
teapot/path.py
teapot/prefix.py
teapot/signature.py
teapot/source.py
teapot/tests.py
teapot.egg-info/PKG-INFO
teapot.egg-info/SOURCES.txt
teapot.egg-info/dependency_links.txt
teapot.egg-info/entry_points.txt
teapot.egg-info/requires.txt
teapot.egg-info/top_level.txt
teapot/extensions/__init__.py
teapot/extensions/builtin.py
teapot/extensions/extension.py
teapot/extra/__init__.py
teapot/extra/rfc6266.py
teapot/fetchers/__init__.py
teapot/fetchers/callbacks.py
teapot/fetchers/fetcher.py
teapot/fetchers/file_fetcher.py
teapot/fetchers/folder_fetcher.py
teapot/fetchers/github_fetcher.py
teapot/fetchers/http_fetcher.py
teapot/filters/__init__.py
teapot/filters/builtin.py
teapot/filters/filter.py
teapot/unpackers/__init__.py
teapot/unpackers/callbacks.py
teapot/unpackers/null_unpacker.py
teapot/unpackers/tarball_unpacker.py
teapot/unpackers/unpacker.py
teapot/unpackers/zipfile_unpacker.py