Metadata-Version: 1.1
Name: teapot
Version: 2.3
Summary: A multi-platform tool to automate the download, unpack and build of third-party softwares.
Home-page: http://teapot-builder.readthedocs.org/en/latest/index.html
Author: Julien Kauffmann
Author-email: julien.kauffmann@freelan.org
License: MIT License
Platform: UNKNOWN
Classifier: Environment :: Console
Classifier: Intended Audience :: Developers
Classifier: Intended Audience :: System Administrators
Classifier: Operating System :: MacOS :: MacOS X
Classifier: Operating System :: Microsoft :: Windows
Classifier: Operating System :: POSIX
Classifier: Programming Language :: Python
Classifier: Topic :: Software Development
Classifier: License :: OSI Approved :: MIT License
